odoo/addons/sms_no_automatic_delete/README.rst
odoo/addons/sms_no_automatic_delete/__init__.py
odoo/addons/sms_no_automatic_delete/__manifest__.py
odoo/addons/sms_no_automatic_delete/data/ir_cron_data.xml
odoo/addons/sms_no_automatic_delete/i18n/sms_no_automatic_delete.pot
odoo/addons/sms_no_automatic_delete/models/__init__.py
odoo/addons/sms_no_automatic_delete/models/sms_sms.py
odoo/addons/sms_no_automatic_delete/readme/CONTRIBUTORS.rst
odoo/addons/sms_no_automatic_delete/readme/DESCRIPTION.rst
odoo/addons/sms_no_automatic_delete/readme/USAGE.rst
odoo/addons/sms_no_automatic_delete/static/description/icon.png
odoo/addons/sms_no_automatic_delete/static/description/index.html
odoo/addons/sms_no_automatic_delete/tests/__init__.py
odoo/addons/sms_no_automatic_delete/tests/test_purge_and_unlink_sms.py
odoo14_addon_sms_no_automatic_delete-14.0.1.1.0.dist-info/METADATA
odoo14_addon_sms_no_automatic_delete-14.0.1.1.0.dist-info/WHEEL
odoo14_addon_sms_no_automatic_delete-14.0.1.1.0.dist-info/top_level.txt
odoo14_addon_sms_no_automatic_delete-14.0.1.1.0.dist-info/RECORD
